langchain_auth/__init__.py
langchain_auth/client.py
langchain_auth/py.typed
langchain_auth/types.py
langchain_auth-0.2.0.dist-info/METADATA
langchain_auth-0.2.0.dist-info/WHEEL
langchain_auth-0.2.0.dist-info/RECORD
